hllrcon/__init__.py
hllrcon/client.py
hllrcon/commands.py
hllrcon/connection.py
hllrcon/exceptions.py
hllrcon/py.typed
hllrcon/rcon.py
hllrcon/responses.py
hllrcon/data/__init__.py
hllrcon/data/_utils.py
hllrcon/data/factions.py
hllrcon/data/game_modes.py
hllrcon/data/layers.py
hllrcon/data/loadouts.py
hllrcon/data/maps.py
hllrcon/data/roles.py
hllrcon/data/sectors.py
hllrcon/data/teams.py
hllrcon/data/vehicles.py
hllrcon/data/weapons.py
hllrcon/protocol/__init__.py
hllrcon/protocol/constants.py
hllrcon/protocol/protocol.py
hllrcon/protocol/request.py
hllrcon/protocol/response.py
hllrcon/sync/__init__.py
hllrcon/sync/commands.py
hllrcon/sync/rcon.py
hllrcon-1.0.1.dist-info/METADATA
hllrcon-1.0.1.dist-info/WHEEL
hllrcon-1.0.1.dist-info/licenses/LICENSE
hllrcon-1.0.1.dist-info/RECORD
