Metadata-Version: 2.4
Name: hllrcon
Version: 1.0.1
Summary: Asynchronous implementation of the Hell Let Loose RCON protocol
Project-URL: Repository, https://github.com/timraay/hllrcon
Project-URL: Issues, https://github.com/timraay/hllrcon/issues
Author: Tim Raaymakers
License-Expression: MIT
License-File: LICENSE
Classifier: Development Status :: 5 - Production/Stable
Classifier: Framework :: AsyncIO
Classifier: Framework :: Pydantic :: 2
Classifier: License :: OSI Approved :: MIT License
Classifier: Operating System :: OS Independent
Classifier: Programming Language :: Python :: 3
Classifier: Programming Language :: Python :: 3 :: Only
Classifier: Programming Language :: Python :: 3.11
Classifier: Programming Language :: Python :: 3.12
Classifier: Programming Language :: Python :: 3.13
Classifier: Programming Language :: Python :: 3.14
Requires-Python: >=3.11
Requires-Dist: pydantic>=2.11.5
Requires-Dist: ty>=0.0.7
Requires-Dist: typing-extensions>=4.13.2
